sceneprogagent/__init__.py
sceneprogagent/planner.py
sceneprogagent/sceneprogagent.py
sceneprogagent/tool.py
sceneprogagent/tool_manager.py
sceneprogagent/utils.py
sceneprogagent-0.1.0.dist-info/METADATA
sceneprogagent-0.1.0.dist-info/WHEEL
sceneprogagent-0.1.0.dist-info/top_level.txt
sceneprogagent-0.1.0.dist-info/RECORD
