Metadata-Version: 2.1
Name: sceneprogagent
Version: 0.1.0
Summary: A Scene Prog Agent
Home-page: https://github.com/KunalMGupta/sceneprogagent.git
Author: Kunal Gupta
Author-email: k5upta@ucsd.edu
Classifier: Programming Language :: Python :: 3
Classifier: License :: OSI Approved :: MIT License
Classifier: Operating System :: OS Independent
Requires-Python: >=3.9
